toil/__init__.py
toil/bus.py
toil/common.py
toil/deferred.py
toil/exceptions.py
toil/job.py
toil/leader.py
toil/realtimeLogger.py
toil/resource.py
toil/serviceManager.py
toil/statsAndLogging.py
toil/toilState.py
toil/version.py
toil/worker.py
toil/batchSystems/__init__.py
toil/batchSystems/abstractBatchSystem.py
toil/batchSystems/abstractGridEngineBatchSystem.py
toil/batchSystems/awsBatch.py
toil/batchSystems/cleanup_support.py
toil/batchSystems/contained_executor.py
toil/batchSystems/gridengine.py
toil/batchSystems/htcondor.py
toil/batchSystems/kubernetes.py
toil/batchSystems/local_support.py
toil/batchSystems/lsf.py
toil/batchSystems/lsfHelper.py
toil/batchSystems/options.py
toil/batchSystems/registry.py
toil/batchSystems/singleMachine.py
toil/batchSystems/slurm.py
toil/batchSystems/torque.py
toil/batchSystems/mesos/__init__.py
toil/batchSystems/mesos/batchSystem.py
toil/batchSystems/mesos/conftest.py
toil/batchSystems/mesos/executor.py
toil/batchSystems/mesos/test/__init__.py
toil/cwl/__init__.py
toil/cwl/conftest.py
toil/cwl/cwltoil.py
toil/cwl/utils.py
toil/fileStores/__init__.py
toil/fileStores/abstractFileStore.py
toil/fileStores/cachingFileStore.py
toil/fileStores/nonCachingFileStore.py
toil/jobStores/__init__.py
toil/jobStores/abstractJobStore.py
toil/jobStores/conftest.py
toil/jobStores/fileJobStore.py
toil/jobStores/googleJobStore.py
toil/jobStores/utils.py
toil/jobStores/aws/__init__.py
toil/jobStores/aws/jobStore.py
toil/jobStores/aws/utils.py
toil/lib/__init__.py
toil/lib/accelerators.py
toil/lib/bioio.py
toil/lib/checksum.py
toil/lib/compatibility.py
toil/lib/conversions.py
toil/lib/directory.py
toil/lib/docker.py
toil/lib/dockstore.py
toil/lib/ec2.py
toil/lib/ec2nodes.py
toil/lib/exceptions.py
toil/lib/expando.py
toil/lib/ftp_utils.py
toil/lib/generatedEC2Lists.py
toil/lib/history.py
toil/lib/history_submission.py
toil/lib/humanize.py
toil/lib/io.py
toil/lib/memoize.py
toil/lib/misc.py
toil/lib/objects.py
toil/lib/pipes.py
toil/lib/plugins.py
toil-9.1.2.dist-info/licenses/LICENSE
toil-9.1.2.dist-info/METADATA
toil-9.1.2.dist-info/WHEEL
toil-9.1.2.dist-info/entry_points.txt
toil-9.1.2.dist-info/top_level.txt
toil-9.1.2.dist-info/RECORD
